Workbook

Sheet Business Summary
A1: Business Summary — GST Sales Dashboard
A3: Business Name | B3: Accessories Business
A4: GSTIN | B4: N/A
A5: Financial Year | B5: FY 2026-27
A7: KPI | B7: Value
A8: Total Invoices | B8: =COUNTA('Sale Invoices'!A3:A1048576)
A9: Total Quantity Sold | B9: =SUM('Sale Invoices'!K:K)
A10: Gross Sale Amount | B10: =SUM('Sale Invoices'!M:M)
A11: Total Discount Given | B11: =SUM('Sale Invoices'!O:O)
A12: Total Taxable Amount | B12: =SUM('Sale Invoices'!P:P)
A13: CGST Total | B13: =SUM('Sale Invoices'!R:R)
A14: SGST Total | B14: =SUM('Sale Invoices'!S:S)
A15: IGST Total | B15: =SUM('Sale Invoices'!T:T)
A16: Total GST Collected | B16: =SUM('Sale Invoices'!U:U)
A17: Total Invoice Value | B17: =SUM('Sale Invoices'!V:V)
A18: Total Cost | B18: =SUM('Sale Invoices'!W:W)
A19: Net Profit | B19: =SUM('Sale Invoices'!X:X)
A20: Profit Margin % | B20: =IFERROR(B19/B17,0)
A21: Average Invoice Value | B21: =IFERROR(B17/B8,0)
A22: Number of Parties | B22: =SUMPRODUCT(('Party-wise Ledger'!A3:A1048576<>"")/COUNTIF('Party-wise Ledger'!A3:A1048576,'Party-wise Ledger'!A3:A1048576&""))

Sheet Sale Invoices
A1: Sale Invoices — Raw Register
A2: Invoice No. | B2: Date | C2: Party Name | D2: Party Type | E2: GSTIN | F2: Party State | G2: Inter-State (Y/N) | H2: Category | I2: Product | J2: HSN/SAC Code | K2: Qty | L2: Unit Price | M2: Gross Amount | N2: Discount % | O2: Discount Amt | P2: Taxable Amount | Q2: GST Rate | R2: CGST | S2: SGST | T2: IGST | U2: Total GST | V2: Invoice Total | W2: Cost | X2: Profit | Y2: Payment Mode
A3: INV201 | B3: 2026-09-10 | C3: ABC Traders | E3: 2160 | H3: Laptop | I3: Laptop | K3: 0 | L3: 0 | M3: 12000 | N3: 5 | O3: 500 | P3: 11500 | Q3: 21.6 | R3: 2160 | S3: 2160 | T3: 2160 | U3: 2160 | V3: 13660 | W3: 0 | X3: 0 | Y3: UPI
A4: INV202 | B4: 2026-09-11 | C4: XYZ Traders | E4: 1530 | H4: Mouse | I4: Mouse | K4: 0 | L4: 0 | M4: 8500 | N4: 2 | O4: 200 | P4: 8300 | Q4: 15.3 | R4: 1530 | S4: 1530 | T4: 1530 | U4: 1530 | V4: 9830 | W4: 0 | X4: 0 | Y4: Cash
A5: INV203 | B5: 2026-09-12 | C5: ABC Traders | E5: 2700 | H5: Keyboard | I5: Keyboard | K5: 0 | L5: 0 | M5: 15000 | N5: 7.5 | O5: 750 | P5: 14250 | Q5: 27 | R5: 2700 | S5: 2700 | T5: 2700 | U5: 2700 | V5: 16950 | W5: 0 | X5: 0 | Y5: Bank
A6: INV204 | B6: 2026-09-13 | C6: DEF Traders | E6: 3960 | H6: Monitor | I6: Monitor | K6: 0 | L6: 0 | M6: 22000 | N6: 10 | O6: 1000 | P6: 21000 | Q6: 39.6 | R6: 3960 | S6: 3960 | T6: 3960 | U6: 3960 | V6: 24960 | W6: 0 | X6: 0 | Y6: UPI

Sheet GST Summary
A1: GST Summary — Rate-wise
A2: GST Rate | B2: Taxable Value | C2: CGST | D2: SGST | E2: IGST | F2: Total GST | G2: Invoice Value
A3: 15.3 | B3: =SUMIF('Sale Invoices'!Q:Q,A3,'Sale Invoices'!P:P) | C3: =SUMIF('Sale Invoices'!Q:Q,A3,'Sale Invoices'!R:R) | D3: =SUMIF('Sale Invoices'!Q:Q,A3,'Sale Invoices'!S:S) | E3: =SUMIF('Sale Invoices'!Q:Q,A3,'Sale Invoices'!T:T) | F3: =SUMIF('Sale Invoices'!Q:Q,A3,'Sale Invoices'!U:U) | G3: =SUMIF('Sale Invoices'!Q:Q,A3,'Sale Invoices'!V:V)
A4: 21.6 | B4: =SUMIF('Sale Invoices'!Q:Q,A4,'Sale Invoices'!P:P) | C4: =SUMIF('Sale Invoices'!Q:Q,A4,'Sale Invoices'!R:R) | D4: =SUMIF('Sale Invoices'!Q:Q,A4,'Sale Invoices'!S:S) | E4: =SUMIF('Sale Invoices'!Q:Q,A4,'Sale Invoices'!T:T) | F4: =SUMIF('Sale Invoices'!Q:Q,A4,'Sale Invoices'!U:U) | G4: =SUMIF('Sale Invoices'!Q:Q,A4,'Sale Invoices'!V:V)
A5: 27 | B5: =SUMIF('Sale Invoices'!Q:Q,A5,'Sale Invoices'!P:P) | C5: =SUMIF('Sale Invoices'!Q:Q,A5,'Sale Invoices'!R:R) | D5: =SUMIF('Sale Invoices'!Q:Q,A5,'Sale Invoices'!S:S) | E5: =SUMIF('Sale Invoices'!Q:Q,A5,'Sale Invoices'!T:T) | F5: =SUMIF('Sale Invoices'!Q:Q,A5,'Sale Invoices'!U:U) | G5: =SUMIF('Sale Invoices'!Q:Q,A5,'Sale Invoices'!V:V)
A6: 39.6 | B6: =SUMIF('Sale Invoices'!Q:Q,A6,'Sale Invoices'!P:P) | C6: =SUMIF('Sale Invoices'!Q:Q,A6,'Sale Invoices'!R:R) | D6: =SUMIF('Sale Invoices'!Q:Q,A6,'Sale Invoices'!S:S) | E6: =SUMIF('Sale Invoices'!Q:Q,A6,'Sale Invoices'!T:T) | F6: =SUMIF('Sale Invoices'!Q:Q,A6,'Sale Invoices'!U:U) | G6: =SUMIF('Sale Invoices'!Q:Q,A6,'Sale Invoices'!V:V)

Sheet HSN Summary
A1: HSN Summary
A2: HSN Code | B2: Category | C2: Total Qty | D2: Taxable Value | E2: Total GST | F2: Total Invoice Value
A3: =SORT(UNIQUE(FILTER('Sale Invoices'!J3:J1048576,'Sale Invoices'!J3:J1048576<>""))) | B3: =IFERROR(INDEX('Sale Invoices'!H:H,MATCH(A3,'Sale Invoices'!J:J,0)),"") | C3: =SUMIF('Sale Invoices'!J:J,A3,'Sale Invoices'!K:K) | D3: =SUMIF('Sale Invoices'!J:J,A3,'Sale Invoices'!P:P) | E3: =SUMIF('Sale Invoices'!J:J,A3,'Sale Invoices'!U:U) | F3: =SUMIF('Sale Invoices'!J:J,A3,'Sale Invoices'!V:V)

Sheet Party-wise Ledger
A1: Party-wise Ledger
A2: Party Name | B2: Type | C2: GSTIN | D2: State | E2: Invoice Count | F2: Taxable Value | G2: GST | H2: Invoice Value | I2: Profit
A3: ABC Traders | B3: Unclassified | C3: 2160 | E3: =COUNTIF('Sale Invoices'!C:C,A3) | F3: =SUMIF('Sale Invoices'!C:C,A3,'Sale Invoices'!P:P) | G3: =SUMIF('Sale Invoices'!C:C,A3,'Sale Invoices'!U:U) | H3: =SUMIF('Sale Invoices'!C:C,A3,'Sale Invoices'!V:V) | I3: =SUMIF('Sale Invoices'!C:C,A3,'Sale Invoices'!X:X)
A4: XYZ Traders | B4: Unclassified | C4: 1530 | E4: =COUNTIF('Sale Invoices'!C:C,A4) | F4: =SUMIF('Sale Invoices'!C:C,A4,'Sale Invoices'!P:P) | G4: =SUMIF('Sale Invoices'!C:C,A4,'Sale Invoices'!U:U) | H4: =SUMIF('Sale Invoices'!C:C,A4,'Sale Invoices'!V:V) | I4: =SUMIF('Sale Invoices'!C:C,A4,'Sale Invoices'!X:X)
A5: DEF Traders | B5: Unclassified | C5: 3960 | E5: =COUNTIF('Sale Invoices'!C:C,A5) | F5: =SUMIF('Sale Invoices'!C:C,A5,'Sale Invoices'!P:P) | G5: =SUMIF('Sale Invoices'!C:C,A5,'Sale Invoices'!U:U) | H5: =SUMIF('Sale Invoices'!C:C,A5,'Sale Invoices'!V:V) | I5: =SUMIF('Sale Invoices'!C:C,A5,'Sale Invoices'!X:X)

Sheet Category Summary
A1: Category Summary
A2: Category | B2: HSN | C2: GST Rate | D2: Qty Sold | E2: Taxable Value | F2: GST | G2: Invoice Value | H2: Profit | I2: Margin %
A3: Laptop | B3: =IFERROR(INDEX('Sale Invoices'!J:J,MATCH(A3,'Sale Invoices'!H:H,0)),"") | C3: =IFERROR(INDEX('Sale Invoices'!Q:Q,MATCH(A3,'Sale Invoices'!H:H,0)),0) | D3: =SUMIF('Sale Invoices'!H:H,A3,'Sale Invoices'!K:K) | E3: =SUMIF('Sale Invoices'!H:H,A3,'Sale Invoices'!P:P) | F3: =SUMIF('Sale Invoices'!H:H,A3,'Sale Invoices'!U:U) | G3: =SUMIF('Sale Invoices'!H:H,A3,'Sale Invoices'!V:V) | H3: =SUMIF('Sale Invoices'!H:H,A3,'Sale Invoices'!X:X) | I3: =IFERROR(H3/G3,0)
A4: Mouse | B4: =IFERROR(INDEX('Sale Invoices'!J:J,MATCH(A4,'Sale Invoices'!H:H,0)),"") | C4: =IFERROR(INDEX('Sale Invoices'!Q:Q,MATCH(A4,'Sale Invoices'!H:H,0)),0) | D4: =SUMIF('Sale Invoices'!H:H,A4,'Sale Invoices'!K:K) | E4: =SUMIF('Sale Invoices'!H:H,A4,'Sale Invoices'!P:P) | F4: =SUMIF('Sale Invoices'!H:H,A4,'Sale Invoices'!U:U) | G4: =SUMIF('Sale Invoices'!H:H,A4,'Sale Invoices'!V:V) | H4: =SUMIF('Sale Invoices'!H:H,A4,'Sale Invoices'!X:X) | I4: =IFERROR(H4/G4,0)
A5: Keyboard | B5: =IFERROR(INDEX('Sale Invoices'!J:J,MATCH(A5,'Sale Invoices'!H:H,0)),"") | C5: =IFERROR(INDEX('Sale Invoices'!Q:Q,MATCH(A5,'Sale Invoices'!H:H,0)),0) | D5: =SUMIF('Sale Invoices'!H:H,A5,'Sale Invoices'!K:K) | E5: =SUMIF('Sale Invoices'!H:H,A5,'Sale Invoices'!P:P) | F5: =SUMIF('Sale Invoices'!H:H,A5,'Sale Invoices'!U:U) | G5: =SUMIF('Sale Invoices'!H:H,A5,'Sale Invoices'!V:V) | H5: =SUMIF('Sale Invoices'!H:H,A5,'Sale Invoices'!X:X) | I5: =IFERROR(H5/G5,0)
A6: Monitor | B6: =IFERROR(INDEX('Sale Invoices'!J:J,MATCH(A6,'Sale Invoices'!H:H,0)),"") | C6: =IFERROR(INDEX('Sale Invoices'!Q:Q,MATCH(A6,'Sale Invoices'!H:H,0)),0) | D6: =SUMIF('Sale Invoices'!H:H,A6,'Sale Invoices'!K:K) | E6: =SUMIF('Sale Invoices'!H:H,A6,'Sale Invoices'!P:P) | F6: =SUMIF('Sale Invoices'!H:H,A6,'Sale Invoices'!U:U) | G6: =SUMIF('Sale Invoices'!H:H,A6,'Sale Invoices'!V:V) | H6: =SUMIF('Sale Invoices'!H:H,A6,'Sale Invoices'!X:X) | I6: =IFERROR(H6/G6,0)

Sheet Payment Mode Summary
A1: Payment Mode Summary
A2: Payment Mode | B2: Invoice Count | C2: Invoice Value | D2: % of Total
A3: UPI | B3: =COUNTIF('Sale Invoices'!Y:Y,A3) | C3: =SUMIF('Sale Invoices'!Y:Y,A3,'Sale Invoices'!V:V) | D3: =IFERROR(=IFERROR(C3/SUM(C:C),0)
A4: Cash | B4: =COUNTIF('Sale Invoices'!Y:Y,A4) | C4: =SUMIF('Sale Invoices'!Y:Y,A4,'Sale Invoices'!V:V) | D4: =IFERROR(=IFERROR(C4/SUM(C:C),0)
A5: Bank | B5: =COUNTIF('Sale Invoices'!Y:Y,A5) | C5: =SUMIF('Sale Invoices'!Y:Y,A5,'Sale Invoices'!V:V) | D5: =IFERROR(=IFERROR(C5/SUM(C:C),0)

Sheet Monthly Trend
A1: Monthly Sales Trend
A2: Month | B2: Invoices | C2: Taxable Value | D2: GST | E2: Invoice Value | F2: Profit
A3: 2026-09 | B3: =SUMPRODUCT(--(LEFT('Sale Invoices'!B:B,7)="2026-09")) | C3: =SUMPRODUCT((LEFT('Sale Invoices'!B:B,7)="2026-09")*'Sale Invoices'!P:P) | D3: =SUMPRODUCT((LEFT('Sale Invoices'!B:B,7)="2026-09")*'Sale Invoices'!U:U) | E3: =SUMPRODUCT((LEFT('Sale Invoices'!B:B,7)="2026-09")*'Sale Invoices'!V:V) | F3: =SUMPRODUCT((LEFT('Sale Invoices'!B:B,7)="2026-09")*'Sale Invoices'!X:X)
