Workbook

Sheet Business Summary
A1: Business Summary — GST Sales Dashboard
A3: Business Name | B3: Accessories Business
A4: GSTIN | B4: N/A
A5: Financial Year | B5: FY 2026-27
A7: KPI | B7: Value
A8: Total Invoices | B8: =COUNTA('Sale Invoices'!A3:A1048576)
A9: Total Quantity Sold | B9: =SUM('Sale Invoices'!K:K)
A10: Gross Sale Amount | B10: =SUM('Sale Invoices'!M:M)
A11: Total Discount Given | B11: =SUM('Sale Invoices'!O:O)
A12: Total Taxable Amount | B12: =SUM('Sale Invoices'!P:P)
A13: CGST Total | B13: =SUM('Sale Invoices'!R:R)
A14: SGST Total | B14: =SUM('Sale Invoices'!S:S)
A15: IGST Total | B15: =SUM('Sale Invoices'!T:T)
A16: Total GST Collected | B16: =SUM('Sale Invoices'!U:U)
A17: Total Invoice Value | B17: =SUM('Sale Invoices'!V:V)
A18: Total Cost | B18: =SUM('Sale Invoices'!W:W)
A19: Net Profit | B19: =SUM('Sale Invoices'!X:X)
A20: Profit Margin % | B20: =IFERROR(B19/B17,0)
A21: Average Invoice Value | B21: =IFERROR(B17/B8,0)
A22: Number of Parties | B22: =SUMPRODUCT(('Party-wise Ledger'!A3:A1048576<>"")/COUNTIF('Party-wise Ledger'!A3:A1048576,'Party-wise Ledger'!A3:A1048576&""))

Sheet Sale Invoices
A1: Sale Invoices — Raw Register
A2: Invoice No. | B2: Date | C2: Party Name | D2: Party Type | E2: GSTIN | F2: Party State | G2: Inter-State (Y/N) | H2: Category | I2: Product | J2: HSN/SAC Code | K2: Qty | L2: Unit Price | M2: Gross Amount | N2: Discount % | O2: Discount Amt | P2: Taxable Amount | Q2: GST Rate | R2: CGST | S2: SGST | T2: IGST | U2: Total GST | V2: Invoice Total | W2: Cost | X2: Profit | Y2: Payment Mode
A3: INV201 | B3: 2026-09-10 | C3: ABC Traders | I3: Laptop | M3: 12000 | O3: 500 | P3: 11500 | U3: 2160 | V3: 13660 | Y3: UPI
A4: INV203 | B4: 2026-09-12 | C4: ABC Traders | I4: Keyboard | M4: 15000 | O4: 750 | P4: 14250 | U4: 2700 | V4: 16950 | Y4: Bank

Sheet GST Summary
A1: GST Summary — Rate-wise
A2: GST Rate | B2: Taxable Value | C2: CGST | D2: SGST | E2: IGST | F2: Total GST | G2: Invoice Value
B3: =SUMIF('Sale Invoices'!Q:Q,"",'Sale Invoices'!P:P) | C3: =SUMIF('Sale Invoices'!Q:Q,"",'Sale Invoices'!R:R) | D3: =SUMIF('Sale Invoices'!Q:Q,"",'Sale Invoices'!S:S) | E3: =SUMIF('Sale Invoices'!Q:Q,"",'Sale Invoices'!T:T) | F3: =SUMIF('Sale Invoices'!Q:Q,"",'Sale Invoices'!U:U) | G3: =SUMIF('Sale Invoices'!Q:Q,"",'Sale Invoices'!V:V)

Sheet HSN Summary
A1: HSN Summary
A2: HSN Code | B2: Category | C2: Total Qty | D2: Taxable Value | E2: Total GST | F2: Total Invoice Value
A3: =SORT(UNIQUE(FILTER('Sale Invoices'!J3:J1048576,'Sale Invoices'!J3:J1048576<>""))) | B3: =IFERROR(INDEX('Sale Invoices'!H:H,MATCH(A3,'Sale Invoices'!J:J,0)),"") | C3: =SUMIF('Sale Invoices'!J:J,A3,'Sale Invoices'!K:K) | D3: =SUMIF('Sale Invoices'!J:J,A3,'Sale Invoices'!P:P) | E3: =SUMIF('Sale Invoices'!J:J,A3,'Sale Invoices'!U:U) | F3: =SUMIF('Sale Invoices'!J:J,A3,'Sale Invoices'!V:V)

Sheet Party-wise Ledger
A1: Party-wise Ledger
A2: Party Name | B2: Type | C2: GSTIN | D2: State | E2: Invoice Count | F2: Taxable Value | G2: GST | H2: Invoice Value | I2: Profit
A3: ABC Traders | B3: Unclassified | C3: Unregistered | E3: =COUNTIF('Sale Invoices'!C:C,A3) | F3: =SUMIF('Sale Invoices'!C:C,A3,'Sale Invoices'!P:P) | G3: =SUMIF('Sale Invoices'!C:C,A3,'Sale Invoices'!U:U) | H3: =SUMIF('Sale Invoices'!C:C,A3,'Sale Invoices'!V:V) | I3: =SUMIF('Sale Invoices'!C:C,A3,'Sale Invoices'!X:X)

Sheet Category Summary
A1: Category Summary
A2: Category | B2: HSN | C2: GST Rate | D2: Qty Sold | E2: Taxable Value | F2: GST | G2: Invoice Value | H2: Profit | I2: Margin %
A3: (Unclassified) | B3: =IFERROR(INDEX('Sale Invoices'!J:J,MATCH(A3,'Sale Invoices'!H:H,0)),"") | C3: =IFERROR(INDEX('Sale Invoices'!Q:Q,MATCH(A3,'Sale Invoices'!H:H,0)),0) | D3: =SUMIF('Sale Invoices'!H:H,A3,'Sale Invoices'!K:K) | E3: =SUMIF('Sale Invoices'!H:H,A3,'Sale Invoices'!P:P) | F3: =SUMIF('Sale Invoices'!H:H,A3,'Sale Invoices'!U:U) | G3: =SUMIF('Sale Invoices'!H:H,A3,'Sale Invoices'!V:V) | H3: =SUMIF('Sale Invoices'!H:H,A3,'Sale Invoices'!X:X) | I3: =IFERROR(H3/G3,0)

Sheet Payment Mode Summary
A1: Payment Mode Summary
A2: Payment Mode | B2: Invoice Count | C2: Invoice Value | D2: % of Total
A3: UPI | B3: =COUNTIF('Sale Invoices'!Y:Y,A3) | C3: =SUMIF('Sale Invoices'!Y:Y,A3,'Sale Invoices'!V:V) | D3: =IFERROR(=IFERROR(C3/SUM(C:C),0)
A4: Bank | B4: =COUNTIF('Sale Invoices'!Y:Y,A4) | C4: =SUMIF('Sale Invoices'!Y:Y,A4,'Sale Invoices'!V:V) | D4: =IFERROR(=IFERROR(C4/SUM(C:C),0)

Sheet Monthly Trend
A1: Monthly Sales Trend
A2: Month | B2: Invoices | C2: Taxable Value | D2: GST | E2: Invoice Value | F2: Profit
A3: 2026-09 | B3: =SUMPRODUCT(--(LEFT('Sale Invoices'!B:B,7)="2026-09")) | C3: =SUMPRODUCT((LEFT('Sale Invoices'!B:B,7)="2026-09")*'Sale Invoices'!P:P) | D3: =SUMPRODUCT((LEFT('Sale Invoices'!B:B,7)="2026-09")*'Sale Invoices'!U:U) | E3: =SUMPRODUCT((LEFT('Sale Invoices'!B:B,7)="2026-09")*'Sale Invoices'!V:V) | F3: =SUMPRODUCT((LEFT('Sale Invoices'!B:B,7)="2026-09")*'Sale Invoices'!X:X)
